llmbrix/__init__.py
llmbrix/chat_history.py
llmbrix/gemini_model.py
llmbrix/tool_agent.py
llmbrix/graph/__init__.py
llmbrix/graph/graph.py
llmbrix/graph/graph_run_context.py
llmbrix/graph/graph_state.py
llmbrix/graph/node.py
llmbrix/graph/node_base.py
llmbrix/graph/router_node.py
llmbrix/msg/__init__.py
llmbrix/msg/base_msg.py
llmbrix/msg/model_msg.py
llmbrix/msg/model_msg_segment.py
llmbrix/msg/model_msg_segment_types.py
llmbrix/msg/tool_msg.py
llmbrix/msg/user_msg.py
llmbrix/msg/user_msg_file_types.py
llmbrix/tool_calling/__init__.py
llmbrix/tool_calling/base_tool.py
llmbrix/tool_calling/tool_executor.py
llmbrix/tool_calling/tool_output.py
llmbrix/tool_calling/tool_param.py
llmbrix/tool_calling/tool_param_types.py
llmbrix/tools/__init__.py
llmbrix/tools/calculator_tool.py
llmbrix/tools/datetime_tool.py
llmbrix-2.0.1.dist-info/licenses/LICENSE
llmbrix-2.0.1.dist-info/METADATA
llmbrix-2.0.1.dist-info/WHEEL
llmbrix-2.0.1.dist-info/top_level.txt
llmbrix-2.0.1.dist-info/RECORD
