Metadata-Version: 2.4
Name: llmbrix
Version: 2.0.1
Summary: Low abstraction agentic LLM framework.
Author-email: Matej Kvassay <matejkvassay5@gmail.com>
Project-URL: Homepage, https://github.com/matejkvassay/LLMBrix
Project-URL: Repository, https://github.com/matejkvassay/LLMBrix
Project-URL: Issues, https://github.com/matejkvassay/LLMBrix/issues
Project-URL: Documentation, https://github.com/matejkvassay/LLMBrix#readme
Keywords: LLM,agent,framework,AI,chatbot,llmbrix,llmbricks
Classifier: Programming Language :: Python :: 3
Classifier: Programming Language :: Python :: 3.11
Classifier: License :: OSI Approved :: Apache Software License
Classifier: Operating System :: OS Independent
Classifier: Development Status :: 3 - Alpha
Classifier: Intended Audience :: Developers
Classifier: Topic :: Software Development :: Libraries
Requires-Python: >=3.11
License-File: LICENSE
Requires-Dist: graphviz
Requires-Dist: pillow
Requires-Dist: google-genai>=1.56.0
Requires-Dist: pydantic
Requires-Dist: sympy
Provides-Extra: dev
Requires-Dist: pytest; extra == "dev"
Requires-Dist: pre-commit; extra == "dev"
Requires-Dist: build; extra == "dev"
Requires-Dist: twine; extra == "dev"
Dynamic: license-file
